nanokits/__init__.py
nanokits-0.0.1.dist-info/LICENSE
nanokits-0.0.1.dist-info/METADATA
nanokits-0.0.1.dist-info/WHEEL
nanokits-0.0.1.dist-info/top_level.txt
nanokits-0.0.1.dist-info/RECORD
